{
  "playlist_index": 11,
  "video_id": "OSYuUqGBQxw",
  "title": "Stanford CS336 Language Modeling from Scratch | Spring 2025 | Lecture 11: Scaling laws 2",
  "duration": 4693,
  "thumbnail": "raw/11_OSYuUqGBQxw/11_OSYuUqGBQxw.jpg",
  "subtitle": "raw/11_OSYuUqGBQxw/11_OSYuUqGBQxw.en-orig.srt",
  "material": "materials/spring2025-lectures/nonexecutable/2025 Lecture 11 - Scaling details.pdf",
  "images": [],
  "transcript_text": "text/11_OSYuUqGBQxw/transcript.txt",
  "official_text": "text/11_OSYuUqGBQxw/official.txt",
  "title_short": "Lecture 11: Scaling laws 2",
  "lecture_dir": "lectures/11_scaling_laws_2"
}